QianduanGongchengshiShouce/README.md
QianduanGongchengshiShouce/__init__.py
QianduanGongchengshiShouce/__main__.py
QianduanGongchengshiShouce/file.epub
QianduanGongchengshiShouce/index.html
QianduanGongchengshiShouce/css/__init__.py
QianduanGongchengshiShouce/css/annotations.css
QianduanGongchengshiShouce/css/main.css
QianduanGongchengshiShouce/css/normalize.css
QianduanGongchengshiShouce/css/popup.css
QianduanGongchengshiShouce/font/__init__.py
QianduanGongchengshiShouce/font/fontello.eot
QianduanGongchengshiShouce/font/fontello.svg
QianduanGongchengshiShouce/font/fontello.ttf
QianduanGongchengshiShouce/font/fontello.woff
QianduanGongchengshiShouce/img/__init__.py
QianduanGongchengshiShouce/img/annotator-glyph-sprite.png
QianduanGongchengshiShouce/img/annotator-icon-sprite.png
QianduanGongchengshiShouce/img/apple-touch-icon.png
QianduanGongchengshiShouce/img/cancelfullscreen.png
QianduanGongchengshiShouce/img/close.png
QianduanGongchengshiShouce/img/fullscreen.png
QianduanGongchengshiShouce/img/loader.gif
QianduanGongchengshiShouce/img/menu-icon.png
QianduanGongchengshiShouce/img/save.png
QianduanGongchengshiShouce/img/saved.png
QianduanGongchengshiShouce/img/settings-s.png
QianduanGongchengshiShouce/img/settings.png
QianduanGongchengshiShouce/img/star.png
QianduanGongchengshiShouce/js/__init__.py
QianduanGongchengshiShouce/js/epub.js
QianduanGongchengshiShouce/js/epub.min.js
QianduanGongchengshiShouce/js/epub.min.map
QianduanGongchengshiShouce/js/hooks.min.js
QianduanGongchengshiShouce/js/hooks.min.map
QianduanGongchengshiShouce/js/reader.js
QianduanGongchengshiShouce/js/reader.js.map
QianduanGongchengshiShouce/js/reader.min.js
QianduanGongchengshiShouce/js/reader.min.map
QianduanGongchengshiShouce/js/hooks/__init__.py
QianduanGongchengshiShouce/js/hooks/extensions/__init__.py
QianduanGongchengshiShouce/js/hooks/extensions/highlight.js
QianduanGongchengshiShouce/js/libs/__init__.py
QianduanGongchengshiShouce/js/libs/jquery.min.js
qianduan_gongchengshi_shouce-2024.3.1.0.dist-info/METADATA
qianduan_gongchengshi_shouce-2024.3.1.0.dist-info/WHEEL
qianduan_gongchengshi_shouce-2024.3.1.0.dist-info/entry_points.txt
qianduan_gongchengshi_shouce-2024.3.1.0.dist-info/top_level.txt
qianduan_gongchengshi_shouce-2024.3.1.0.dist-info/RECORD
